{
    "Computer":  "FRWSTH",
    "Customer":  "Dev Machine",
    "OS":  "Microsoft Windows 11 Pro",
    "CPUPercent":  3.7,
    "CPUTooltip":  "Top CPU Processes:\nMemory Compression: 480.4s CPU time, 2.19GB RAM\nCursor: 7949.4s CPU time, 0.53GB RAM\nSentinelAgent: 16654.5s CPU time, 0.52GB RAM\nchrome: 8401.7s CPU time, 0.5GB RAM\nchrome: 1662.8s CPU time, 0.46GB RAM\nchrome: 1458s CPU time, 0.46GB RAM\nchrome: 175.1s CPU time, 0.32GB RAM\nchrome: 1804.2s CPU time, 0.31GB RAM\nexplorer: 6607.6s CPU time, 0.31GB RAM\nchrome: 304.6s CPU time, 0.31GB RAM",
    "TopCPUProcesses":  [
                            {
                                "Memory":  2.19,
                                "CPU":  480.4,
                                "Name":  "Memory Compression"
                            },
                            {
                                "Memory":  0.53,
                                "CPU":  7949.4,
                                "Name":  "Cursor"
                            },
                            {
                                "Memory":  0.52,
                                "CPU":  16654.5,
                                "Name":  "SentinelAgent"
                            },
                            {
                                "Memory":  0.5,
                                "CPU":  8401.7,
                                "Name":  "chrome"
                            },
                            {
                                "Memory":  0.46,
                                "CPU":  1662.8,
                                "Name":  "chrome"
                            },
                            {
                                "Memory":  0.46,
                                "CPU":  1458,
                                "Name":  "chrome"
                            },
                            {
                                "Memory":  0.32,
                                "CPU":  175.1,
                                "Name":  "chrome"
                            },
                            {
                                "Memory":  0.31,
                                "CPU":  1804.2,
                                "Name":  "chrome"
                            },
                            {
                                "Memory":  0.31,
                                "CPU":  6607.6,
                                "Name":  "explorer"
                            },
                            {
                                "Memory":  0.31,
                                "CPU":  304.6,
                                "Name":  "chrome"
                            }
                        ],
    "RAMTotalGB":  31.8,
    "RAMUsedGB":  16.8,
    "RAMUsedPercent":  52.8,
    "RAMFreeGB":  15,
    "DiskFreePercent":  47.8,
    "TotalSize":  "237.1GB",
    "DiskTooltip":  "Total Storage: 237.1GB\n\nDisk Usage:\nC:\\ - Used: 123.9GB, Free: 113.3GB of 237.1GB (47.8% free)",
    "Volumes":  {
                    "Label":  "",
                    "FreePercent":  47.8,
                    "TotalSize":  "237.1GB",
                    "SizeBytes":  254616268800,
                    "FreeSize":  "113.3GB",
                    "UsedSize":  "123.9GB",
                    "Letter":  "C"
                },
    "Uptime":  "6d 21h 1m",
    "UptimeTooltip":  "Boot Time: 2025-10-21 14:02:40\nSystem has been running for:\n6 days, 21 hours, 1 minutes",
    "BootTime":  "\/Date(1761080560000)\/",
    "NetworkMbps":  0.28,
    "NetworkTooltip":  "Avg Throughput (5s):\nSent: 0.12 Mbps\nReceived: 0.16 Mbps\nTotal: 0.28 Mbps",
    "UpdateStatus":  "Up-to-date",
    "UpdateCount":  0,
    "UpdateTooltip":  "No pending updates found.",
    "LastPoll":  "10/27 11:03"
}