{
    "Computer":  "FRWSTH",
    "Customer":  "Dev Machine",
    "OS":  "Microsoft Windows 11 Pro",
    "CPUPercent":  5.3,
    "CPUTooltip":  "Top CPU Processes:\nSentinelAgent: 18298s CPU time, 0.73GB RAM\nMemory Compression: 243.7s CPU time, 0.63GB RAM\nchrome: 11.1s CPU time, 0.44GB RAM\nchrome: 9.5s CPU time, 0.44GB RAM\nchrome: 7.5s CPU time, 0.32GB RAM\nexplorer: 716.4s CPU time, 0.32GB RAM\nchrome: 15.2s CPU time, 0.31GB RAM\nchrome: 6.5s CPU time, 0.28GB RAM\nchrome: 3s CPU time, 0.23GB RAM\nmsedge: 198.1s CPU time, 0.2GB RAM",
    "TopCPUProcesses":  [
                            {
                                "Memory":  0.73,
                                "CPU":  18298,
                                "Name":  "SentinelAgent"
                            },
                            {
                                "Memory":  0.63,
                                "CPU":  243.7,
                                "Name":  "Memory Compression"
                            },
                            {
                                "Memory":  0.44,
                                "CPU":  11.1,
                                "Name":  "chrome"
                            },
                            {
                                "Memory":  0.44,
                                "CPU":  9.5,
                                "Name":  "chrome"
                            },
                            {
                                "Memory":  0.32,
                                "CPU":  7.5,
                                "Name":  "chrome"
                            },
                            {
                                "Memory":  0.32,
                                "CPU":  716.4,
                                "Name":  "explorer"
                            },
                            {
                                "Memory":  0.31,
                                "CPU":  15.2,
                                "Name":  "chrome"
                            },
                            {
                                "Memory":  0.28,
                                "CPU":  6.5,
                                "Name":  "chrome"
                            },
                            {
                                "Memory":  0.23,
                                "CPU":  3,
                                "Name":  "chrome"
                            },
                            {
                                "Memory":  0.2,
                                "CPU":  198.1,
                                "Name":  "msedge"
                            }
                        ],
    "RAMTotalGB":  31.8,
    "RAMUsedGB":  11.2,
    "RAMUsedPercent":  35.2,
    "RAMFreeGB":  20.6,
    "DiskFreePercent":  50.6,
    "TotalSize":  "237.1GB",
    "DiskTooltip":  "Total Storage: 237.1GB\n\nDisk Usage:\nC:\\ - Used: 117.2GB, Free: 119.9GB of 237.1GB (50.6% free)",
    "Volumes":  {
                    "Label":  "",
                    "FreePercent":  50.6,
                    "TotalSize":  "237.1GB",
                    "SizeBytes":  254616268800,
                    "FreeSize":  "119.9GB",
                    "UsedSize":  "117.2GB",
                    "Letter":  "C"
                },
    "Uptime":  "7d 23h 43m",
    "UptimeTooltip":  "Boot Time: 2025-09-22 08:20:10\nSystem has been running for:\n7 days, 23 hours, 43 minutes",
    "BootTime":  "\/Date(1758554410000)\/",
    "NetworkMbps":  0.27,
    "NetworkTooltip":  "Avg Throughput (5s):\nSent: 0.07 Mbps\nReceived: 0.2 Mbps\nTotal: 0.27 Mbps",
    "UpdateStatus":  "Up-to-date",
    "UpdateCount":  0,
    "UpdateTooltip":  "No pending updates found.",
    "LastPoll":  "09/29 08:04"
}