{
    "Computer":  "FRWSTH",
    "Customer":  "Dev Machine",
    "OS":  "Microsoft Windows 11 Pro",
    "CPUPercent":  14,
    "CPUTooltip":  "Top CPU Processes:\nSentinelAgent: 5384.9s CPU time, 0.65GB RAM\nchrome: 174.4s CPU time, 0.42GB RAM\nchrome: 180.1s CPU time, 0.39GB RAM\nPlayControlClient: 121.8s CPU time, 0.35GB RAM\nchrome: 54.5s CPU time, 0.34GB RAM\nchrome: 36.5s CPU time, 0.32GB RAM\nchrome: 117.7s CPU time, 0.32GB RAM\nchrome: 485.1s CPU time, 0.32GB RAM\nchrome: 7.1s CPU time, 0.28GB RAM\nchrome: 21.2s CPU time, 0.27GB RAM",
    "TopCPUProcesses":  [
                            {
                                "Memory":  0.65,
                                "CPU":  5384.9,
                                "Name":  "SentinelAgent"
                            },
                            {
                                "Memory":  0.42,
                                "CPU":  174.4,
                                "Name":  "chrome"
                            },
                            {
                                "Memory":  0.39,
                                "CPU":  180.1,
                                "Name":  "chrome"
                            },
                            {
                                "Memory":  0.35,
                                "CPU":  121.8,
                                "Name":  "PlayControlClient"
                            },
                            {
                                "Memory":  0.34,
                                "CPU":  54.5,
                                "Name":  "chrome"
                            },
                            {
                                "Memory":  0.32,
                                "CPU":  36.5,
                                "Name":  "chrome"
                            },
                            {
                                "Memory":  0.32,
                                "CPU":  117.7,
                                "Name":  "chrome"
                            },
                            {
                                "Memory":  0.32,
                                "CPU":  485.1,
                                "Name":  "chrome"
                            },
                            {
                                "Memory":  0.28,
                                "CPU":  7.1,
                                "Name":  "chrome"
                            },
                            {
                                "Memory":  0.27,
                                "CPU":  21.2,
                                "Name":  "chrome"
                            }
                        ],
    "RAMTotalGB":  31.8,
    "RAMUsedGB":  12.3,
    "RAMUsedPercent":  38.7,
    "RAMFreeGB":  19.5,
    "DiskFreePercent":  43.4,
    "TotalSize":  "237.1GB",
    "DiskTooltip":  "Total Storage: 237.1GB\n\nDisk Usage:\nC:\\ - Used: 134.2GB, Free: 102.9GB of 237.1GB (43.4% free)",
    "Volumes":  {
                    "Label":  "",
                    "FreePercent":  43.4,
                    "TotalSize":  "237.1GB",
                    "SizeBytes":  254616268800,
                    "FreeSize":  "102.9GB",
                    "UsedSize":  "134.2GB",
                    "Letter":  "C"
                },
    "Uptime":  "2d 5h 14m",
    "UptimeTooltip":  "Boot Time: 2025-11-01 04:04:27\nSystem has been running for:\n2 days, 5 hours, 14 minutes",
    "BootTime":  "\/Date(1761995067000)\/",
    "NetworkMbps":  1.02,
    "NetworkTooltip":  "Avg Throughput (5s):\nSent: 0.12 Mbps\nReceived: 0.9 Mbps\nTotal: 1.02 Mbps",
    "UpdateStatus":  "Up-to-date",
    "UpdateCount":  0,
    "UpdateTooltip":  "No pending updates found.",
    "LastPoll":  "11/03 09:19"
}