{
    "Computer":  "FRWSTH",
    "Customer":  "Dev Machine",
    "OS":  "Microsoft Windows 11 Pro",
    "CPUPercent":  11.5,
    "CPUTooltip":  "Top CPU Processes:\nMemory Compression: 581.5s CPU time, 2.21GB RAM\nCursor: 11250.5s CPU time, 0.57GB RAM\nchrome: 9382.6s CPU time, 0.56GB RAM\nSentinelAgent: 20030.8s CPU time, 0.54GB RAM\nchrome: 1715.7s CPU time, 0.5GB RAM\nchrome: 1822.2s CPU time, 0.47GB RAM\nchrome: 121.2s CPU time, 0.4GB RAM\nchrome: 2193.2s CPU time, 0.38GB RAM\nexplorer: 6847.1s CPU time, 0.32GB RAM\nchrome: 243.5s CPU time, 0.32GB RAM",
    "TopCPUProcesses":  [
                            {
                                "Memory":  2.21,
                                "CPU":  581.5,
                                "Name":  "Memory Compression"
                            },
                            {
                                "Memory":  0.57,
                                "CPU":  11250.5,
                                "Name":  "Cursor"
                            },
                            {
                                "Memory":  0.56,
                                "CPU":  9382.6,
                                "Name":  "chrome"
                            },
                            {
                                "Memory":  0.54,
                                "CPU":  20030.8,
                                "Name":  "SentinelAgent"
                            },
                            {
                                "Memory":  0.5,
                                "CPU":  1715.7,
                                "Name":  "chrome"
                            },
                            {
                                "Memory":  0.47,
                                "CPU":  1822.2,
                                "Name":  "chrome"
                            },
                            {
                                "Memory":  0.4,
                                "CPU":  121.2,
                                "Name":  "chrome"
                            },
                            {
                                "Memory":  0.38,
                                "CPU":  2193.2,
                                "Name":  "chrome"
                            },
                            {
                                "Memory":  0.32,
                                "CPU":  6847.1,
                                "Name":  "explorer"
                            },
                            {
                                "Memory":  0.32,
                                "CPU":  243.5,
                                "Name":  "chrome"
                            }
                        ],
    "RAMTotalGB":  31.8,
    "RAMUsedGB":  19.7,
    "RAMUsedPercent":  61.9,
    "RAMFreeGB":  12.1,
    "DiskFreePercent":  47.2,
    "TotalSize":  "237.1GB",
    "DiskTooltip":  "Total Storage: 237.1GB\n\nDisk Usage:\nC:\\ - Used: 125.2GB, Free: 112GB of 237.1GB (47.2% free)",
    "Volumes":  {
                    "Label":  "",
                    "FreePercent":  47.2,
                    "TotalSize":  "237.1GB",
                    "SizeBytes":  254616268800,
                    "FreeSize":  "112GB",
                    "UsedSize":  "125.2GB",
                    "Letter":  "C"
                },
    "Uptime":  "6d 7h 31m",
    "UptimeTooltip":  "Boot Time: 2025-10-21 14:02:40\nSystem has been running for:\n6 days, 7 hours, 31 minutes",
    "BootTime":  "\/Date(1761080560000)\/",
    "NetworkMbps":  0.99,
    "NetworkTooltip":  "Avg Throughput (5s):\nSent: 0.16 Mbps\nReceived: 0.83 Mbps\nTotal: 0.99 Mbps",
    "UpdateStatus":  "Up-to-date",
    "UpdateCount":  0,
    "UpdateTooltip":  "No pending updates found.",
    "LastPoll":  "10/27 21:33"
}