{
    "Computer":  "RECOVERYHYPERV",
    "Customer":  "Clawson Honda",
    "OS":  "Microsoft Windows Server 2019 Standard",
    "CPUPercent":  16.8,
    "CPUTooltip":  "Top CPU Processes:\nSentinelAgent: 270078.7s CPU time, 0.49GB RAM\nMsMpEng: 76892.2s CPU time, 0.33GB RAM\nvmconnect: 29.9s CPU time, 0.24GB RAM\nexplorer: 4404.4s CPU time, 0.22GB RAM\nAgentService: 3137373.9s CPU time, 0.21GB RAM\nsvchost: 18913.9s CPU time, 0.18GB RAM\npowershell: 177.6s CPU time, 0.18GB RAM\nSecure System: 0s CPU time, 0.15GB RAM\nSystem: 371929.7s CPU time, 0.13GB RAM\nsvchost: 1281.6s CPU time, 0.12GB RAM",
    "TopCPUProcesses":  [
                            {
                                "Memory":  0.49,
                                "CPU":  270078.7,
                                "Name":  "SentinelAgent"
                            },
                            {
                                "Memory":  0.33,
                                "CPU":  76892.2,
                                "Name":  "MsMpEng"
                            },
                            {
                                "Memory":  0.24,
                                "CPU":  29.9,
                                "Name":  "vmconnect"
                            },
                            {
                                "Memory":  0.22,
                                "CPU":  4404.4,
                                "Name":  "explorer"
                            },
                            {
                                "Memory":  0.21,
                                "CPU":  3137373.9,
                                "Name":  "AgentService"
                            },
                            {
                                "Memory":  0.18,
                                "CPU":  18913.9,
                                "Name":  "svchost"
                            },
                            {
                                "Memory":  0.18,
                                "CPU":  177.6,
                                "Name":  "powershell"
                            },
                            {
                                "Memory":  0.15,
                                "CPU":  0,
                                "Name":  "Secure System"
                            },
                            {
                                "Memory":  0.13,
                                "CPU":  371929.7,
                                "Name":  "System"
                            },
                            {
                                "Memory":  0.12,
                                "CPU":  1281.6,
                                "Name":  "svchost"
                            }
                        ],
    "RAMTotalGB":  72,
    "RAMUsedGB":  26.3,
    "RAMUsedPercent":  36.5,
    "RAMFreeGB":  45.7,
    "DiskFreePercent":  16,
    "TotalSize":  "1.3TB",
    "DiskTooltip":  "Total Storage: 1.3TB\n\nDisk Usage:\nF:\\ (DataStore) - Used: 1.1TB, Free: 10.5GB of 1.1TB (1% free)\nC:\\ - Used: 64.9GB, Free: 208GB of 272.9GB (76.2% free)",
    "Volumes":  [
                    {
                        "Label":  "DataStore",
                        "FreePercent":  1,
                        "TotalSize":  "1.1TB",
                        "SizeBytes":  1174252023808,
                        "FreeSize":  "10.5GB",
                        "UsedSize":  "1.1TB",
                        "Letter":  "F"
                    },
                    {
                        "Label":  "",
                        "FreePercent":  76.2,
                        "TotalSize":  "272.9GB",
                        "SizeBytes":  292985761792,
                        "FreeSize":  "208GB",
                        "UsedSize":  "64.9GB",
                        "Letter":  "C"
                    }
                ],
    "Uptime":  "62d 22h 50m",
    "UptimeTooltip":  "Boot Time: 2025-07-09 15:04:32\nSystem has been running for:\n62 days, 22 hours, 50 minutes",
    "BootTime":  "\/Date(1752098672000)\/",
    "NetworkMbps":  26.04,
    "NetworkTooltip":  "Avg Throughput (5s):\nSent: 11.92 Mbps\nReceived: 14.12 Mbps\nTotal: 26.04 Mbps",
    "UpdateStatus":  "4 Updates",
    "UpdateCount":  4,
    "UpdateTooltip":  "Click for details on 4 pending updates.",
    "LastPoll":  "09/09 13:55"
}