{
    "Computer":  "SANSERV2019",
    "Customer":  "Jose Sanchez, DDS",
    "OS":  "Microsoft Windows Server 2019 Standard",
    "CPUPercent":  25.8,
    "CPUTooltip":  "Top CPU Processes:\nctreesql: 109947.9s CPU time, 2.92GB RAM\nSentinelAgent: 18863.9s CPU time, 0.68GB RAM\nSSPService: 97135.9s CPU time, 0.47GB RAM\nMsMpEng: 66901.9s CPU time, 0.38GB RAM\nsvchost: 10697.5s CPU time, 0.35GB RAM\nRegistry: 41.1s CPU time, 0.24GB RAM\nSophosFileScanner: 353.4s CPU time, 0.22GB RAM\nDentrixUpdaterService: 1389.2s CPU time, 0.14GB RAM\nSystem: 31133.9s CPU time, 0.14GB RAM\ndns: 168.6s CPU time, 0.14GB RAM",
    "TopCPUProcesses":  [
                            {
                                "Memory":  2.92,
                                "CPU":  109947.9,
                                "Name":  "ctreesql"
                            },
                            {
                                "Memory":  0.68,
                                "CPU":  18863.9,
                                "Name":  "SentinelAgent"
                            },
                            {
                                "Memory":  0.47,
                                "CPU":  97135.9,
                                "Name":  "SSPService"
                            },
                            {
                                "Memory":  0.38,
                                "CPU":  66901.9,
                                "Name":  "MsMpEng"
                            },
                            {
                                "Memory":  0.35,
                                "CPU":  10697.5,
                                "Name":  "svchost"
                            },
                            {
                                "Memory":  0.24,
                                "CPU":  41.1,
                                "Name":  "Registry"
                            },
                            {
                                "Memory":  0.22,
                                "CPU":  353.4,
                                "Name":  "SophosFileScanner"
                            },
                            {
                                "Memory":  0.14,
                                "CPU":  1389.2,
                                "Name":  "DentrixUpdaterService"
                            },
                            {
                                "Memory":  0.14,
                                "CPU":  31133.9,
                                "Name":  "System"
                            },
                            {
                                "Memory":  0.14,
                                "CPU":  168.6,
                                "Name":  "dns"
                            }
                        ],
    "RAMTotalGB":  15.7,
    "RAMUsedGB":  11.3,
    "RAMUsedPercent":  72,
    "RAMFreeGB":  4.4,
    "DiskFreePercent":  89.7,
    "TotalSize":  "3.6TB",
    "DiskTooltip":  "Total Storage: 3.6TB\n\nDisk Usage:\nC:\\ (OS) - Used: 116.2GB, Free: 383.8GB of 500GB (76.8% free)\nD:\\ (DATA) - Used: 266.2GB, Free: 2.9TB of 3.1TB (91.7% free)",
    "Volumes":  [
                    {
                        "Label":  "OS",
                        "FreePercent":  76.8,
                        "TotalSize":  "500GB",
                        "SizeBytes":  536870907904,
                        "FreeSize":  "383.8GB",
                        "UsedSize":  "116.2GB",
                        "Letter":  "C"
                    },
                    {
                        "Label":  "DATA",
                        "FreePercent":  91.7,
                        "TotalSize":  "3.1TB",
                        "SizeBytes":  3459786993664,
                        "FreeSize":  "2.9TB",
                        "UsedSize":  "266.2GB",
                        "Letter":  "D"
                    }
                ],
    "Uptime":  "32d 21h 47m",
    "UptimeTooltip":  "Boot Time: 2025-09-11 17:37:31\nSystem has been running for:\n32 days, 21 hours, 47 minutes",
    "BootTime":  "\/Date(1757637451000)\/",
    "NetworkMbps":  2,
    "NetworkTooltip":  "Avg Throughput (5s):\nSent: 1.77 Mbps\nReceived: 0.23 Mbps\nTotal: 2 Mbps",
    "UpdateStatus":  "1 Updates",
    "UpdateCount":  1,
    "UpdateTooltip":  "Click for details on 1 pending updates.",
    "LastPoll":  "10/13 15:24"
}