{
    "Computer":  "SANSERV2019",
    "Customer":  "Jose Sanchez, DDS",
    "OS":  "Microsoft Windows Server 2019 Standard",
    "CPUPercent":  25.4,
    "CPUTooltip":  "Top CPU Processes:\nctreesql: 22869.8s CPU time, 1.6GB RAM\nSSPService: 19046s CPU time, 0.37GB RAM\nMsMpEng: 11848.6s CPU time, 0.37GB RAM\nRegistry: 7s CPU time, 0.24GB RAM\nSophosFileScanner: 299.4s CPU time, 0.2GB RAM\ndns: 28.7s CPU time, 0.13GB RAM\nHSPS.eServices.DigitalHighway.Services: 64.8s CPU time, 0.11GB RAM\nDentrixUpdaterService: 253.9s CPU time, 0.11GB RAM\nDentrixClientService: 176.5s CPU time, 0.1GB RAM\nSystem: 5744.1s CPU time, 0.1GB RAM",
    "TopCPUProcesses":  [
                            {
                                "Memory":  1.6,
                                "CPU":  22869.8,
                                "Name":  "ctreesql"
                            },
                            {
                                "Memory":  0.37,
                                "CPU":  19046,
                                "Name":  "SSPService"
                            },
                            {
                                "Memory":  0.37,
                                "CPU":  11848.6,
                                "Name":  "MsMpEng"
                            },
                            {
                                "Memory":  0.24,
                                "CPU":  7,
                                "Name":  "Registry"
                            },
                            {
                                "Memory":  0.2,
                                "CPU":  299.4,
                                "Name":  "SophosFileScanner"
                            },
                            {
                                "Memory":  0.13,
                                "CPU":  28.7,
                                "Name":  "dns"
                            },
                            {
                                "Memory":  0.11,
                                "CPU":  64.8,
                                "Name":  "HSPS.eServices.DigitalHighway.Services"
                            },
                            {
                                "Memory":  0.11,
                                "CPU":  253.9,
                                "Name":  "DentrixUpdaterService"
                            },
                            {
                                "Memory":  0.1,
                                "CPU":  176.5,
                                "Name":  "DentrixClientService"
                            },
                            {
                                "Memory":  0.1,
                                "CPU":  5744.1,
                                "Name":  "System"
                            }
                        ],
    "RAMTotalGB":  15.7,
    "RAMUsedGB":  8.2,
    "RAMUsedPercent":  52.2,
    "RAMFreeGB":  7.5,
    "DiskFreePercent":  91.2,
    "TotalSize":  "3.6TB",
    "DiskTooltip":  "Total Storage: 3.6TB\n\nDisk Usage:\nC:\\ (OS) - Used: 59.8GB, Free: 440.2GB of 500GB (88% free)\nD:\\ (DATA) - Used: 266.3GB, Free: 2.9TB of 3.1TB (91.7% free)",
    "Volumes":  [
                    {
                        "Label":  "OS",
                        "FreePercent":  88,
                        "TotalSize":  "500GB",
                        "SizeBytes":  536870907904,
                        "FreeSize":  "440.2GB",
                        "UsedSize":  "59.8GB",
                        "Letter":  "C"
                    },
                    {
                        "Label":  "DATA",
                        "FreePercent":  91.7,
                        "TotalSize":  "3.1TB",
                        "SizeBytes":  3459786993664,
                        "FreeSize":  "2.9TB",
                        "UsedSize":  "266.3GB",
                        "Letter":  "D"
                    }
                ],
    "Uptime":  "7d 20h 33m",
    "UptimeTooltip":  "Boot Time: 2025-09-02 16:40:55\nSystem has been running for:\n7 days, 20 hours, 33 minutes",
    "BootTime":  "\/Date(1756856455000)\/",
    "NetworkMbps":  0.69,
    "NetworkTooltip":  "Avg Throughput (5s):\nSent: 0.35 Mbps\nReceived: 0.34 Mbps\nTotal: 0.69 Mbps",
    "UpdateStatus":  "3 Updates",
    "UpdateCount":  3,
    "UpdateTooltip":  "Click for details on 3 pending updates.",
    "LastPoll":  "09/09 13:14"
}