{
    "Computer":  "VSDC1",
    "Customer":  "Clawson Honda",
    "OS":  "Microsoft Windows Server 2019 Standard",
    "CPUPercent":  10.2,
    "CPUTooltip":  "Top CPU Processes:\nSentinelAgent: 53915.6s CPU time, 0.65GB RAM\nMsMpEng: 40344.8s CPU time, 0.26GB RAM\nlsass: 19085.7s CPU time, 0.25GB RAM\nRegistry: 45s CPU time, 0.24GB RAM\nsvchost: 11380.8s CPU time, 0.2GB RAM\nncstreamer: 987.7s CPU time, 0.15GB RAM\ndns: 7534.6s CPU time, 0.14GB RAM\nNinjaRMMAgent: 47774.3s CPU time, 0.13GB RAM\nncstreamer: 372.7s CPU time, 0.1GB RAM\npowershell: 3.5s CPU time, 0.1GB RAM",
    "TopCPUProcesses":  [
                            {
                                "Memory":  0.65,
                                "CPU":  53915.6,
                                "Name":  "SentinelAgent"
                            },
                            {
                                "Memory":  0.26,
                                "CPU":  40344.8,
                                "Name":  "MsMpEng"
                            },
                            {
                                "Memory":  0.25,
                                "CPU":  19085.7,
                                "Name":  "lsass"
                            },
                            {
                                "Memory":  0.24,
                                "CPU":  45,
                                "Name":  "Registry"
                            },
                            {
                                "Memory":  0.2,
                                "CPU":  11380.8,
                                "Name":  "svchost"
                            },
                            {
                                "Memory":  0.15,
                                "CPU":  987.7,
                                "Name":  "ncstreamer"
                            },
                            {
                                "Memory":  0.14,
                                "CPU":  7534.6,
                                "Name":  "dns"
                            },
                            {
                                "Memory":  0.13,
                                "CPU":  47774.3,
                                "Name":  "NinjaRMMAgent"
                            },
                            {
                                "Memory":  0.1,
                                "CPU":  372.7,
                                "Name":  "ncstreamer"
                            },
                            {
                                "Memory":  0.1,
                                "CPU":  3.5,
                                "Name":  "powershell"
                            }
                        ],
    "RAMTotalGB":  16,
    "RAMUsedGB":  5.8,
    "RAMUsedPercent":  36.2,
    "RAMFreeGB":  10.2,
    "DiskFreePercent":  70.7,
    "TotalSize":  "199.4GB",
    "DiskTooltip":  "Total Storage: 199.4GB\n\nDisk Usage:\nC:\\ - Used: 58.3GB, Free: 141.1GB of 199.4GB (70.7% free)",
    "Volumes":  {
                    "Label":  "",
                    "FreePercent":  70.7,
                    "TotalSize":  "199.4GB",
                    "SizeBytes":  214102437888,
                    "FreeSize":  "141.1GB",
                    "UsedSize":  "58.3GB",
                    "Letter":  "C"
                },
    "Uptime":  "11d 8h 39m",
    "UptimeTooltip":  "Boot Time: 2025-10-24 06:23:19\nSystem has been running for:\n11 days, 8 hours, 39 minutes",
    "BootTime":  "\/Date(1761312199000)\/",
    "NetworkMbps":  0.54,
    "NetworkTooltip":  "Avg Throughput (5s):\nSent: 0.42 Mbps\nReceived: 0.12 Mbps\nTotal: 0.54 Mbps",
    "UpdateStatus":  "1 Updates",
    "UpdateCount":  1,
    "UpdateTooltip":  "Click for details on 1 pending updates.",
    "LastPoll":  "11/04 15:02"
}