{
    "Computer":  "VSDC1",
    "Customer":  "Clawson Honda",
    "OS":  "Microsoft Windows Server 2019 Standard",
    "CPUPercent":  26.4,
    "CPUTooltip":  "Top CPU Processes:\nSentinelAgent: 14756s CPU time, 0.58GB RAM\nlsass: 6137.7s CPU time, 0.32GB RAM\nMsMpEng: 8416.8s CPU time, 0.26GB RAM\nefsvss-2008-r2-x64: 131.9s CPU time, 0.14GB RAM\ndns: 1758.9s CPU time, 0.13GB RAM\nRegistry: 18.1s CPU time, 0.1GB RAM\npowershell: 2.7s CPU time, 0.1GB RAM\nsvchost: 3056.1s CPU time, 0.1GB RAM\nNinjaRMMAgent: 5376.4s CPU time, 0.08GB RAM\nSentinelStaticEngineScanner: 3s CPU time, 0.08GB RAM",
    "TopCPUProcesses":  [
                            {
                                "Memory":  0.58,
                                "CPU":  14756,
                                "Name":  "SentinelAgent"
                            },
                            {
                                "Memory":  0.32,
                                "CPU":  6137.7,
                                "Name":  "lsass"
                            },
                            {
                                "Memory":  0.26,
                                "CPU":  8416.8,
                                "Name":  "MsMpEng"
                            },
                            {
                                "Memory":  0.14,
                                "CPU":  131.9,
                                "Name":  "efsvss-2008-r2-x64"
                            },
                            {
                                "Memory":  0.13,
                                "CPU":  1758.9,
                                "Name":  "dns"
                            },
                            {
                                "Memory":  0.1,
                                "CPU":  18.1,
                                "Name":  "Registry"
                            },
                            {
                                "Memory":  0.1,
                                "CPU":  2.7,
                                "Name":  "powershell"
                            },
                            {
                                "Memory":  0.1,
                                "CPU":  3056.1,
                                "Name":  "svchost"
                            },
                            {
                                "Memory":  0.08,
                                "CPU":  5376.4,
                                "Name":  "NinjaRMMAgent"
                            },
                            {
                                "Memory":  0.08,
                                "CPU":  3,
                                "Name":  "SentinelStaticEngineScanner"
                            }
                        ],
    "RAMTotalGB":  16,
    "RAMUsedGB":  4.9,
    "RAMUsedPercent":  30.6,
    "RAMFreeGB":  11.1,
    "DiskFreePercent":  70.2,
    "TotalSize":  "199.4GB",
    "DiskTooltip":  "Total Storage: 199.4GB\n\nDisk Usage:\nC:\\ - Used: 59.4GB, Free: 140GB of 199.4GB (70.2% free)",
    "Volumes":  {
                    "Label":  "",
                    "FreePercent":  70.2,
                    "TotalSize":  "199.4GB",
                    "SizeBytes":  214102437888,
                    "FreeSize":  "140GB",
                    "UsedSize":  "59.4GB",
                    "Letter":  "C"
                },
    "Uptime":  "3d 20h 54m",
    "UptimeTooltip":  "Boot Time: 2025-10-16 04:28:00\nSystem has been running for:\n3 days, 20 hours, 54 minutes",
    "BootTime":  "\/Date(1760614080000)\/",
    "NetworkMbps":  0.33999999999999997,
    "NetworkTooltip":  "Avg Throughput (5s):\nSent: 0.22 Mbps\nReceived: 0.12 Mbps\nTotal: 0.34 Mbps",
    "UpdateStatus":  "1 Updates",
    "UpdateCount":  1,
    "UpdateTooltip":  "Click for details on 1 pending updates.",
    "LastPoll":  "10/19 01:22"
}