{
    "Computer":  "VSDC1",
    "Customer":  "Clawson Honda",
    "OS":  "Microsoft Windows Server 2019 Standard",
    "CPUPercent":  30.5,
    "CPUTooltip":  "Top CPU Processes:\nsvchost: 43566.7s CPU time, 0.6GB RAM\nSentinelAgent: 90083.7s CPU time, 0.51GB RAM\nMsMpEng: 41177.1s CPU time, 0.24GB RAM\ndns: 26716.4s CPU time, 0.18GB RAM\nexplorer: 2012.2s CPU time, 0.18GB RAM\nSearchUI: 39.4s CPU time, 0.17GB RAM\nlsass: 65439.2s CPU time, 0.17GB RAM\nRegistry: 153.5s CPU time, 0.12GB RAM\nAgentService: 61669.1s CPU time, 0.11GB RAM\nsvchost: 1778.3s CPU time, 0.1GB RAM",
    "TopCPUProcesses":  [
                            {
                                "Memory":  0.6,
                                "CPU":  43566.7,
                                "Name":  "svchost"
                            },
                            {
                                "Memory":  0.51,
                                "CPU":  90083.7,
                                "Name":  "SentinelAgent"
                            },
                            {
                                "Memory":  0.24,
                                "CPU":  41177.1,
                                "Name":  "MsMpEng"
                            },
                            {
                                "Memory":  0.18,
                                "CPU":  26716.4,
                                "Name":  "dns"
                            },
                            {
                                "Memory":  0.18,
                                "CPU":  2012.2,
                                "Name":  "explorer"
                            },
                            {
                                "Memory":  0.17,
                                "CPU":  39.4,
                                "Name":  "SearchUI"
                            },
                            {
                                "Memory":  0.17,
                                "CPU":  65439.2,
                                "Name":  "lsass"
                            },
                            {
                                "Memory":  0.12,
                                "CPU":  153.5,
                                "Name":  "Registry"
                            },
                            {
                                "Memory":  0.11,
                                "CPU":  61669.1,
                                "Name":  "AgentService"
                            },
                            {
                                "Memory":  0.1,
                                "CPU":  1778.3,
                                "Name":  "svchost"
                            }
                        ],
    "RAMTotalGB":  16,
    "RAMUsedGB":  7,
    "RAMUsedPercent":  43.8,
    "RAMFreeGB":  9,
    "DiskFreePercent":  61.6,
    "TotalSize":  "199.4GB",
    "DiskTooltip":  "Total Storage: 199.4GB\n\nDisk Usage:\nC:\\ - Used: 76.5GB, Free: 122.9GB of 199.4GB (61.6% free)",
    "Volumes":  {
                    "Label":  "",
                    "FreePercent":  61.6,
                    "TotalSize":  "199.4GB",
                    "SizeBytes":  214102437888,
                    "FreeSize":  "122.9GB",
                    "UsedSize":  "76.5GB",
                    "Letter":  "C"
                },
    "Uptime":  "40d 1h 19m",
    "UptimeTooltip":  "Boot Time: 2025-08-22 00:07:32\nSystem has been running for:\n40 days, 1 hours, 19 minutes",
    "BootTime":  "\/Date(1755846452000)\/",
    "NetworkMbps":  14.23,
    "NetworkTooltip":  "Avg Throughput (5s):\nSent: 13.82 Mbps\nReceived: 0.41 Mbps\nTotal: 14.23 Mbps",
    "UpdateStatus":  "2 Updates",
    "UpdateCount":  2,
    "UpdateTooltip":  "Click for details on 2 pending updates.",
    "LastPoll":  "10/01 01:27"
}