{
    "Computer":  "VSPS1",
    "Customer":  "Clawson Honda",
    "OS":  "Microsoft Windows Server 2019 Standard",
    "CPUPercent":  4.9,
    "CPUTooltip":  "Top CPU Processes:\nprintfilterpipelinesvc: 918.6s CPU time, 0.41GB RAM\nSentinelAgent: 15174.7s CPU time, 0.34GB RAM\nMsMpEng: 15373.6s CPU time, 0.33GB RAM\nchrome: 152s CPU time, 0.18GB RAM\nMsSense: 5275.3s CPU time, 0.16GB RAM\nchrome: 5.3s CPU time, 0.14GB RAM\nsvchost: 3514.9s CPU time, 0.11GB RAM\nchrome: 76.7s CPU time, 0.1GB RAM\npowershell: 1.7s CPU time, 0.1GB RAM\nncstreamer: 0.9s CPU time, 0.1GB RAM",
    "TopCPUProcesses":  [
                            {
                                "Memory":  0.41,
                                "CPU":  918.6,
                                "Name":  "printfilterpipelinesvc"
                            },
                            {
                                "Memory":  0.34,
                                "CPU":  15174.7,
                                "Name":  "SentinelAgent"
                            },
                            {
                                "Memory":  0.33,
                                "CPU":  15373.6,
                                "Name":  "MsMpEng"
                            },
                            {
                                "Memory":  0.18,
                                "CPU":  152,
                                "Name":  "chrome"
                            },
                            {
                                "Memory":  0.16,
                                "CPU":  5275.3,
                                "Name":  "MsSense"
                            },
                            {
                                "Memory":  0.14,
                                "CPU":  5.3,
                                "Name":  "chrome"
                            },
                            {
                                "Memory":  0.11,
                                "CPU":  3514.9,
                                "Name":  "svchost"
                            },
                            {
                                "Memory":  0.1,
                                "CPU":  76.7,
                                "Name":  "chrome"
                            },
                            {
                                "Memory":  0.1,
                                "CPU":  1.7,
                                "Name":  "powershell"
                            },
                            {
                                "Memory":  0.1,
                                "CPU":  0.9,
                                "Name":  "ncstreamer"
                            }
                        ],
    "RAMTotalGB":  16,
    "RAMUsedGB":  5.3,
    "RAMUsedPercent":  33.1,
    "RAMFreeGB":  10.7,
    "DiskFreePercent":  63.1,
    "TotalSize":  "126.4GB",
    "DiskTooltip":  "Total Storage: 126.4GB\n\nDisk Usage:\nC:\\ - Used: 46.7GB, Free: 79.7GB of 126.4GB (63.1% free)",
    "Volumes":  {
                    "Label":  "",
                    "FreePercent":  63.1,
                    "TotalSize":  "126.4GB",
                    "SizeBytes":  135719284736,
                    "FreeSize":  "79.7GB",
                    "UsedSize":  "46.7GB",
                    "Letter":  "C"
                },
    "Uptime":  "5d 20h 10m",
    "UptimeTooltip":  "Boot Time: 2025-10-17 04:26:43\nSystem has been running for:\n5 days, 20 hours, 10 minutes",
    "BootTime":  "\/Date(1760700403000)\/",
    "NetworkMbps":  0.36,
    "NetworkTooltip":  "Avg Throughput (5s):\nSent: 0.22 Mbps\nReceived: 0.14 Mbps\nTotal: 0.36 Mbps",
    "UpdateStatus":  "2 Updates",
    "UpdateCount":  2,
    "UpdateTooltip":  "Click for details on 2 pending updates.",
    "LastPoll":  "10/22 00:37"
}