{
    "Computer":  "VSPS1",
    "Customer":  "Clawson Honda",
    "OS":  "Microsoft Windows Server 2019 Standard",
    "CPUPercent":  25.4,
    "CPUTooltip":  "Top CPU Processes:\nSentinelAgent: 126753.5s CPU time, 0.63GB RAM\nMsMpEng: 64321.7s CPU time, 0.3GB RAM\nWmiPrvSE: 61624.6s CPU time, 0.28GB RAM\nMsSense: 65269.4s CPU time, 0.25GB RAM\nexplorer: 260.5s CPU time, 0.19GB RAM\nSearchUI: 32.8s CPU time, 0.17GB RAM\nRegistry: 187.2s CPU time, 0.13GB RAM\nsvchost: 4014.5s CPU time, 0.12GB RAM\nspoolsv: 90577s CPU time, 0.12GB RAM\nsvchost: 1196.8s CPU time, 0.1GB RAM",
    "TopCPUProcesses":  [
                            {
                                "Memory":  0.63,
                                "CPU":  126753.5,
                                "Name":  "SentinelAgent"
                            },
                            {
                                "Memory":  0.3,
                                "CPU":  64321.7,
                                "Name":  "MsMpEng"
                            },
                            {
                                "Memory":  0.28,
                                "CPU":  61624.6,
                                "Name":  "WmiPrvSE"
                            },
                            {
                                "Memory":  0.25,
                                "CPU":  65269.4,
                                "Name":  "MsSense"
                            },
                            {
                                "Memory":  0.19,
                                "CPU":  260.5,
                                "Name":  "explorer"
                            },
                            {
                                "Memory":  0.17,
                                "CPU":  32.8,
                                "Name":  "SearchUI"
                            },
                            {
                                "Memory":  0.13,
                                "CPU":  187.2,
                                "Name":  "Registry"
                            },
                            {
                                "Memory":  0.12,
                                "CPU":  4014.5,
                                "Name":  "svchost"
                            },
                            {
                                "Memory":  0.12,
                                "CPU":  90577,
                                "Name":  "spoolsv"
                            },
                            {
                                "Memory":  0.1,
                                "CPU":  1196.8,
                                "Name":  "svchost"
                            }
                        ],
    "RAMTotalGB":  16,
    "RAMUsedGB":  6.2,
    "RAMUsedPercent":  38.8,
    "RAMFreeGB":  9.8,
    "DiskFreePercent":  62.6,
    "TotalSize":  "126.4GB",
    "DiskTooltip":  "Total Storage: 126.4GB\n\nDisk Usage:\nC:\\ - Used: 47.3GB, Free: 79.1GB of 126.4GB (62.6% free)",
    "Volumes":  {
                    "Label":  "",
                    "FreePercent":  62.6,
                    "TotalSize":  "126.4GB",
                    "SizeBytes":  135719284736,
                    "FreeSize":  "79.1GB",
                    "UsedSize":  "47.3GB",
                    "Letter":  "C"
                },
    "Uptime":  "47d 20h 9m",
    "UptimeTooltip":  "Boot Time: 2025-08-22 01:52:33\nSystem has been running for:\n47 days, 20 hours, 9 minutes",
    "BootTime":  "\/Date(1755852753000)\/",
    "NetworkMbps":  1.12,
    "NetworkTooltip":  "Avg Throughput (5s):\nSent: 0.54 Mbps\nReceived: 0.58 Mbps\nTotal: 1.12 Mbps",
    "UpdateStatus":  "3 Updates",
    "UpdateCount":  3,
    "UpdateTooltip":  "Click for details on 3 pending updates.",
    "LastPoll":  "10/07 22:02"
}