{
    "Computer":  "VSPS1",
    "Customer":  "Clawson Honda",
    "OS":  "Microsoft Windows Server 2019 Standard",
    "CPUPercent":  13.3,
    "CPUTooltip":  "Top CPU Processes:\nSentinelAgent: 7371.3s CPU time, 0.62GB RAM\nMsMpEng: 42259.3s CPU time, 0.31GB RAM\nMsSense: 17013.7s CPU time, 0.22GB RAM\npowershell: 17.3s CPU time, 0.18GB RAM\nchrome: 928.9s CPU time, 0.18GB RAM\nexplorer: 62.4s CPU time, 0.18GB RAM\nSearchUI: 7.1s CPU time, 0.16GB RAM\nsvchost: 4646s CPU time, 0.15GB RAM\nRegistry: 48.6s CPU time, 0.13GB RAM\nWmiPrvSE: 16380.3s CPU time, 0.12GB RAM",
    "TopCPUProcesses":  [
                            {
                                "Memory":  0.62,
                                "CPU":  7371.3,
                                "Name":  "SentinelAgent"
                            },
                            {
                                "Memory":  0.31,
                                "CPU":  42259.3,
                                "Name":  "MsMpEng"
                            },
                            {
                                "Memory":  0.22,
                                "CPU":  17013.7,
                                "Name":  "MsSense"
                            },
                            {
                                "Memory":  0.18,
                                "CPU":  17.3,
                                "Name":  "powershell"
                            },
                            {
                                "Memory":  0.18,
                                "CPU":  928.9,
                                "Name":  "chrome"
                            },
                            {
                                "Memory":  0.18,
                                "CPU":  62.4,
                                "Name":  "explorer"
                            },
                            {
                                "Memory":  0.16,
                                "CPU":  7.1,
                                "Name":  "SearchUI"
                            },
                            {
                                "Memory":  0.15,
                                "CPU":  4646,
                                "Name":  "svchost"
                            },
                            {
                                "Memory":  0.13,
                                "CPU":  48.6,
                                "Name":  "Registry"
                            },
                            {
                                "Memory":  0.12,
                                "CPU":  16380.3,
                                "Name":  "WmiPrvSE"
                            }
                        ],
    "RAMTotalGB":  16,
    "RAMUsedGB":  6.2,
    "RAMUsedPercent":  38.8,
    "RAMFreeGB":  9.8,
    "DiskFreePercent":  64.8,
    "TotalSize":  "126.4GB",
    "DiskTooltip":  "Total Storage: 126.4GB\n\nDisk Usage:\nC:\\ - Used: 44.5GB, Free: 81.9GB of 126.4GB (64.8% free)",
    "Volumes":  {
                    "Label":  "",
                    "FreePercent":  64.8,
                    "TotalSize":  "126.4GB",
                    "SizeBytes":  135719284736,
                    "FreeSize":  "81.9GB",
                    "UsedSize":  "44.5GB",
                    "Letter":  "C"
                },
    "Uptime":  "14d 16h 18m",
    "UptimeTooltip":  "Boot Time: 2025-08-22 01:52:33\nSystem has been running for:\n14 days, 16 hours, 18 minutes",
    "BootTime":  "\/Date(1755852753000)\/",
    "NetworkMbps":  0.01,
    "NetworkTooltip":  "Avg Throughput (5s):\nSent: 0.01 Mbps\nReceived: 0 Mbps\nTotal: 0.01 Mbps",
    "UpdateStatus":  "3 Updates",
    "UpdateCount":  3,
    "UpdateTooltip":  "Click for details on 3 pending updates.",
    "LastPoll":  "09/04 18:11"
}